pyzipcin/__init__.py
pyzipcin/db/__init__.py
pyzipcin/db/constants.py
pyzipcin/db/createDB.py
pyzipcin/db/migrateDB.py
pyzipcin/modules/__init__.py
pyzipcin/modules/base.py
pyzipcin/modules/constants.py
pyzipcin/modules/database.db
pyzipcin/modules/zdecode.py
pyzipcin/modules/zencode.py
pyzipcin/modules/zvalidate.py
pyzipcin-0.2.2.dist-info/LICENSE.txt
pyzipcin-0.2.2.dist-info/METADATA
pyzipcin-0.2.2.dist-info/WHEEL
pyzipcin-0.2.2.dist-info/top_level.txt
pyzipcin-0.2.2.dist-info/RECORD
