Metadata-Version: 2.1
Name: pyzipcin
Version: 0.2.2
Summary: A python3 library providing information of ZIP codes of India as well as Verify Pincode based on data from data.gov.in(2019)
Home-page: https://github.com/ravigoel08/pyzipcin
Author: CodewithRv
Author-email: ravigoel.1997@gmail.com
License: MIT
Keywords: india,zipcodes,pincode,data.gov.in,pyzipcin
Platform: UNKNOWN
Classifier: Intended Audience :: Developers
Classifier: Topic :: Software Development :: Build Tools
Classifier: License :: OSI Approved :: MIT License
Classifier: Programming Language :: Python :: 3
Classifier: Programming Language :: Python :: 3.4
Classifier: Programming Language :: Python :: 3.5
Classifier: Programming Language :: Python :: 3.6
Classifier: Programming Language :: Python :: 3.9
Classifier: Operating System :: OS Independent
Requires-Dist: sqlalchemy
